horns/__init__.py
horns-0.6.0.dist-info/LICENSE
horns-0.6.0.dist-info/METADATA
horns-0.6.0.dist-info/WHEEL
horns-0.6.0.dist-info/RECORD
