Metadata-Version: 2.1
Name: horns
Version: 0.6.0
Summary: Horn's parallel analysis in Python.
Home-page: https://github.com/sammosummo/Horns
License: MIT
Keywords: psychology,psychometrics,factor analysis,parallel analysis,eigenvalues,eigenvectors
Author: Sam Mathias
Requires-Python: >=3.11,<4.0
Classifier: License :: OSI Approved :: MIT License
Classifier: Programming Language :: Python :: 3
Classifier: Programming Language :: Python :: 3.11
Requires-Dist: numba-stats (>=1.7.0,<2.0.0)
Requires-Dist: numpy (>=1.26.4,<2.0.0)
Requires-Dist: scipy (>=1.12.0,<2.0.0)
Requires-Dist: tqdm (>=4.66.2,<5.0.0)
Project-URL: Documentation, https://github.com/sammosummo/Horns
Project-URL: Repository, https://github.com/sammosummo/Horns
